docs/__init__.py
docs/docs_examples/__init__.py
docs/docs_examples/catboost_example.py
docs/docs_examples/classification_lightgbm.py
docs/docs_examples/classification_sklearn.py
docs/docs_examples/hdbscan_example.py
docs/docs_examples/lightgbm_example.py
docs/docs_examples/quick_start.py
docs/docs_examples/regression_lightgbm.py
docs/docs_examples/regression_sklearn.py
docs/docs_examples/xgboost_example.py
goldilox/__init__.py
goldilox/config.py
goldilox/pipeline.py
goldilox/utils.py
goldilox/app/__init__.py
goldilox/app/cli.py
goldilox/app/main.py
goldilox/sklearn/__init__.py
goldilox/sklearn/pipeline.py
goldilox/sklearn/utils.py
goldilox/vaex/__init__.py
goldilox/vaex/pipeline.py
goldilox/vaex/core/__init__.py
goldilox/vaex/core/utils.py
goldilox/vaex/core/variables.py
goldilox/vaex/transformers/__init__.py
goldilox/vaex/transformers/_keras.py
goldilox/vaex/transformers/_transformers.py
goldilox/vaex/transformers/_wv.py
goldilox/vaex/transformers/_xlearn.py
goldilox/vaex/transformers/image.py
tests/__init__.py
tests/catboost_test.py
tests/flaml_test.py
tests/hdbscan_test.py
tests/imperio_test.py
tests/implicit_test.py
tests/lightfm_test.py
tests/lightgbm_test.py
tests/nearest_neighbors_test.py
tests/ops_test.py
tests/persistance_test.py
tests/river_test.py
tests/skleran_tests.py
tests/test_utils.py
tests/text_test.py
tests/vaex_tests.py
tests/xgboost_test.py
goldilox-0.0.1a8.dist-info/METADATA
goldilox-0.0.1a8.dist-info/WHEEL
goldilox-0.0.1a8.dist-info/entry_points.txt
goldilox-0.0.1a8.dist-info/top_level.txt
goldilox-0.0.1a8.dist-info/RECORD
